publicmethod/__init__.py
publicmethod/_version.py
publicmethod/core/__init__.py
publicmethod/core/base_component.py
publicmethod/core/data_reader.py
publicmethod/core/log_config.py
publicmethod/core/path_manager.py
publicmethod-0.1.4.dist-info/licenses/LICENSE
publicmethod-0.1.4.dist-info/METADATA
publicmethod-0.1.4.dist-info/WHEEL
publicmethod-0.1.4.dist-info/top_level.txt
publicmethod-0.1.4.dist-info/RECORD
