Metadata-Version: 2.4
Name: publicmethod
Version: 0.1.4
Summary: 通用Python组件库，提供数据读取、路径管理和日志功能
Author-email: Zhou Yuanqi <zyq1034378361@gmail.com>
License: MIT
Project-URL: Homepage, https://github.com/1034378361/publicmethod
Project-URL: Bug Tracker, https://github.com/1034378361/publicmethod/issues
Classifier: Programming Language :: Python :: 3
Classifier: License :: OSI Approved :: MIT License
Classifier: Operating System :: OS Independent
Requires-Python: >=3.8
License-File: LICENSE
Provides-Extra: dev
Requires-Dist: pytest>=7.4.3; extra == "dev"
Requires-Dist: black>=23.11.0; extra == "dev"
Requires-Dist: flake8>=6.1.0; extra == "dev"
Requires-Dist: mypy>=1.7.0; extra == "dev"
Requires-Dist: setuptools_scm>=6.2.0; extra == "dev"
Requires-Dist: pytest-cov>=4.1.0; extra == "dev"
Dynamic: license-file
